humblpatito/__init__.py
humblpatito/_docs.py
humblpatito/database.py
humblpatito/duckdb.py
humblpatito/exceptions.py
humblpatito/polars.py
humblpatito/pydantic.py
humblpatito/sql.py
humblpatito/validators.py
humblpatito/xdg.py
humblpatito-0.7.3.dist-info/LICENSE
humblpatito-0.7.3.dist-info/METADATA
humblpatito-0.7.3.dist-info/WHEEL
humblpatito-0.7.3.dist-info/RECORD
