Metadata-Version: 2.1
Name: humblpatito
Version: 0.7.3
Summary: A dataframe modelling library built on top of polars and pydantic.
Home-page: https://github.com/kolonialno/patito
License: MIT
Keywords: validation,dataframe
Author: Jakob Gerhard Martinussen
Author-email: jakobgm@gmail.com
Requires-Python: >=3.8,<4.0
Classifier: License :: OSI Approved :: MIT License
Classifier: Programming Language :: Python :: 3
Classifier: Programming Language :: Python :: 3.8
Classifier: Programming Language :: Python :: 3.9
Classifier: Programming Language :: Python :: 3.10
Classifier: Programming Language :: Python :: 3.11
Provides-Extra: caching
Provides-Extra: docs
Provides-Extra: duckdb
Provides-Extra: pandas
Requires-Dist: Sphinx (<7) ; extra == "docs"
Requires-Dist: duckdb (>=0.6.0) ; (python_version >= "3.8" and python_version < "4.0") and (extra == "duckdb")
Requires-Dist: nox (>=2023.4.22,<2024.0.0)
Requires-Dist: pandas ; (python_version >= "3.8" and python_version < "4.0") and (extra == "pandas")
Requires-Dist: polars (>=0.19.0)
Requires-Dist: pyarrow (>=5.0.0) ; (python_version >= "3.8" and python_version < "4.0") and (extra == "caching" or extra == "duckdb")
Requires-Dist: pydantic (>=2.0.0)
Requires-Dist: sphinx-autobuild ; extra == "docs"
Requires-Dist: sphinx-autodoc-typehints ; extra == "docs"
Requires-Dist: sphinx-rtd-theme ; extra == "docs"
Requires-Dist: sphinx-toolbox ; extra == "docs"
Requires-Dist: sphinxcontrib-mermaid ; extra == "docs"
Requires-Dist: typing-extensions
Project-URL: Documentation, https://patito.readthedocs.io
Project-URL: Repository, https://github.com/kolonialno/patito
